summac/__init__.py
summac/benchmark.py
summac/model_baseline.py
summac/model_guardrails.py
summac/model_summac.py
summac/run_baseline.py
summac/train_summac.py
summac/utils_misc.py
summac/utils_optim.py
summac/utils_scorer.py
summac/utils_scoring.py
summac-0.0.4.dist-info/LICENSE
summac-0.0.4.dist-info/METADATA
summac-0.0.4.dist-info/WHEEL
summac-0.0.4.dist-info/top_level.txt
summac-0.0.4.dist-info/RECORD
