Metadata-Version: 2.1
Name: summac
Version: 0.0.4
Summary: UNKNOWN
Home-page: UNKNOWN
License: Apache
Platform: UNKNOWN
License-File: LICENSE
Requires-Dist: torch
Requires-Dist: transformers (>=4.24.0)
Requires-Dist: nltk (>=3.6.6)
Requires-Dist: huggingface-hub (<=0.17.0)
Requires-Dist: sentencepiece
Requires-Dist: protobuf
